educelab/mets/__init__.py
educelab/mets/behavior.py
educelab/mets/constants.py
educelab/mets/document.py
educelab/mets/exceptions.py
educelab/mets/file_sec.py
educelab/mets/generic.py
educelab/mets/header.py
educelab/mets/metadata.py
educelab/mets/structure.py
educelab/mets/utils.py
educelab/mets/schemas/__init__.py
educelab/mets/schemas/mets-1.12.1.xsd
educelab/mets_gui/__init__.py
educelab/mets_gui/behaviour_tab.py
educelab/mets_gui/constants.py
educelab/mets_gui/convertor.py
educelab/mets_gui/dialogs.py
educelab/mets_gui/file_tab.py
educelab/mets_gui/header_tab.py
educelab/mets_gui/links_tab.py
educelab/mets_gui/main.py
educelab/mets_gui/metadata_tab.py
educelab/mets_gui/mets_tab.py
educelab/mets_gui/resources.py
educelab/mets_gui/storage.py
educelab/mets_gui/structure_tab.py
educelab/mets_gui/utils.py
educelab/mets_gui/res/icon_add.png
educelab/mets_gui/res/icon_app.png
educelab/mets_gui/res/icon_child_add.png
educelab/mets_gui/res/icon_edit.png
educelab/mets_gui/res/icon_info.png
educelab/mets_gui/res/icon_info.svg
educelab/mets_gui/res/icon_remove.png
educelab_mets-0.5.0.dist-info/METADATA
educelab_mets-0.5.0.dist-info/WHEEL
educelab_mets-0.5.0.dist-info/entry_points.txt
educelab_mets-0.5.0.dist-info/top_level.txt
educelab_mets-0.5.0.dist-info/RECORD
