Metadata-Version: 2.1
Name: educelab-mets
Version: 0.5.0
Summary: EduceLab METS profile library and tools
Home-page: https://gitlab.com/educelab/mets-tools
Author: Seth Parker
Author-email: c.seth.parker@uky.edu
Classifier: Programming Language :: Python :: 3
Classifier: Programming Language :: Python :: 3.9
Classifier: Programming Language :: Python :: 3.10
Classifier: Operating System :: OS Independent
Requires-Python: >=3.9
Requires-Dist: lxml
Requires-Dist: PySide6
